{
  "image_id": 2,
  "image_url": "https://cs.stanford.edu/people/rak248/VG_100K_2/2.jpg",
  "objects": [
    {
      "synsets": [
        "road.n.01"
      ],
      "h": 254,
      "object_id": 1023841,
      "merged_object_ids": [],
      "names": [
        "road"
      ],
      "w": 364,
      "y": 345,
      "x": 0
    },
    {
      "synsets": [
        "sidewalk.n.01"
      ],
      "h": 253,
      "object_id": 1023813,
      "merged_object_ids": [],
      "names": [
        "sidewalk"
      ],
      "w": 478,
      "y": 347,
      "x": 320
    },
    {
      "synsets": [
        "building.n.01"
      ],
      "h": 414,
      "object_id": 1023819,
      "merged_object_ids": [],
      "names": [
        "building"
      ],
      "w": 228,
      "y": 0,
      "x": 569
    },
    {
      "synsets": [
        "building.n.01"
      ],
      "h": 319,
      "object_id": 1023846,
      "merged_object_ids": [],
      "names": [
        "building"
      ],
      "w": 258,
      "y": 0,
      "x": 171
    },
    {
      "synsets": [],
      "h": 412,
      "object_id": 1023845,
      "merged_object_ids": [],
      "names": [
        "street light"
      ],
      "w": 114,
      "y": 120,
      "x": 386
    },
    {
      "synsets": [
        "crossing.n.05"
      ],
      "h": 68,
      "object_id": 5077,
      "merged_object_ids": [],
      "names": [
        "crosswalk"
      ],
      "w": 366,
      "y": 531,
      "x": 0
    },
    {
      "synsets": [
        "man.n.01"
      ],
      "h": 246,
      "object_id": 1023838,
      "merged_object_ids": [],
      "names": [
        "man"
      ],
      "w": 142,
      "y": 325,
      "x": 321
    },
    {
      "synsets": [
        "pole.n.01"
      ],
      "h": 533,
      "object_id": 1023847,
      "merged_object_ids": [],
      "names": [
        "pole"
      ],
      "w": 49,
      "y": 0,
      "x": 423
    },
    {
      "synsets": [
        "window.n.01"
      ],
      "h": 165,
      "object_id": 5080,
      "merged_object_ids": [],
      "names": [
        "window"
      ],
      "w": 94,
      "y": 68,
      "x": 649
    },
    {
      "synsets": [
        "car.n.01"
      ],
      "h": 108,
      "object_id": 1023836,
      "merged_object_ids": [],
      "names": [
        "car"
      ],
      "w": 127,
      "y": 354,
      "x": 240
    },
    {
      "synsets": [
        "tree.n.01"
      ],
      "h": 220,
      "object_id": 5074,
      "merged_object_ids": [],
      "names": [
        "tree"
      ],
      "w": 89,
      "y": 146,
      "x": 0
    },
    {
      "synsets": [
        "tree.n.01"
      ],
      "h": 161,
      "object_id": 5076,
      "merged_object_ids": [],
      "names": [
        "tree"
      ],
      "w": 106,
      "y": 195,
      "x": 102
    },
    {
      "synsets": [
        "tree.n.01"
      ],
      "h": 205,
      "object_id": 5075,
      "merged_object_ids": [],
      "names": [
        "tree"
      ],
      "w": 62,
      "y": 155,
      "x": 58
    },
    {
      "synsets": [
        "window.n.01"
      ],
      "h": 110,
      "object_id": 5082,
      "merged_object_ids": [],
      "names": [
        "window"
      ],
      "w": 98,
      "y": 263,
      "x": 644
    },
    {
      "synsets": [
        "window.n.01"
      ],
      "h": 161,
      "object_id": 5081,
      "merged_object_ids": [],
      "names": [
        "window"
      ],
      "w": 53,
      "y": 71,
      "x": 746
    },
    {
      "synsets": [
        "car.n.01"
      ],
      "h": 61,
      "object_id": 5085,
      "merged_object_ids": [],
      "names": [
        "car"
      ],
      "w": 81,
      "y": 337,
      "x": 350
    },
    {
      "synsets": [
        "backpack.n.01"
      ],
      "h": 80,
      "object_id": 5071,
      "merged_object_ids": [],
      "names": [
        "backpack"
      ],
      "w": 70,
      "y": 362,
      "x": 361
    },
    {
      "synsets": [
        "window.n.01"
      ],
      "h": 107,
      "object_id": 5083,
      "merged_object_ids": [],
      "names": [
        "window"
      ],
      "w": 49,
      "y": 264,
      "x": 750
    },
    {
      "synsets": [
        "gym_shoe.n.01"
      ],
      "h": 24,
      "object_id": 5088,
      "merged_object_ids": [],
      "names": [
        "sneakers"
      ],
      "w": 40,
      "y": 541,
      "x": 338
    },
    {
      "synsets": [
        "window.n.01"
      ],
      "h": 170,
      "object_id": 5084,
      "merged_object_ids": [],
      "names": [
        "window"
      ],
      "w": 18,
      "y": 73,
      "x": 631
    },
    {
      "synsets": [],
      "h": 12,
      "object_id": 5069,
      "merged_object_ids": [
        5090
      ],
      "names": [
        "walk sign"
      ],
      "w": 27,
      "y": 195,
      "x": 473
    },
    {
      "synsets": [],
      "h": 126,
      "object_id": 5086,
      "merged_object_ids": [],
      "names": [
        "street light"
      ],
      "w": 27,
      "y": 217,
      "x": 292
    },
    {
      "synsets": [
        "bicycle.n.01"
      ],
      "h": 63,
      "object_id": 5089,
      "merged_object_ids": [],
      "names": [
        "bike"
      ],
      "w": 47,
      "y": 405,
      "x": 418
    },
    {
      "synsets": [
        "sign.n.02"
      ],
      "h": 62,
      "object_id": 1023823,
      "merged_object_ids": [],
      "names": [
        "sign"
      ],
      "w": 14,
      "y": 288,
      "x": 233
    },
    {
      "synsets": [
        "light.n.02"
      ],
      "h": 16,
      "object_id": 1023848,
      "merged_object_ids": [],
      "names": [
        "lights"
      ],
      "w": 14,
      "y": 288,
      "x": 233
    }
  ]
}